README.md
setup.py
pytdx/__init__.py
pytdx/base_socket_client.py
pytdx/errors.py
pytdx/exhq.py
pytdx/heartbeat.py
pytdx/helper.py
pytdx/hq.py
pytdx/log.py
pytdx/params.py
pytdx/async/__init__.py
pytdx/async/async_base_socket_client.py
pytdx/async/hq.py
pytdx/async/pool.py
pytdx/async/reflection.py
pytdx/bin/__init__.py
pytdx/bin/get_tdx_trader_server.py
pytdx/bin/hqbenchmark.py
pytdx/bin/hqget.py
pytdx/bin/hqreader.py
pytdx/config/__init__.py
pytdx/config/hosts.py
pytdx/parser/__init__.py
pytdx/parser/base.py
pytdx/parser/ex_get_history_instrument_bars_range.py
pytdx/parser/ex_get_history_minute_time_data.py
pytdx/parser/ex_get_history_transaction_data.py
pytdx/parser/ex_get_instrument_bars.py
pytdx/parser/ex_get_instrument_count.py
pytdx/parser/ex_get_instrument_info.py
pytdx/parser/ex_get_instrument_quote.py
pytdx/parser/ex_get_instrument_quote_list.py
pytdx/parser/ex_get_markets.py
pytdx/parser/ex_get_minute_time_data.py
pytdx/parser/ex_get_transaction_data.py
pytdx/parser/ex_setup_commands.py
pytdx/parser/get_block_info.py
pytdx/parser/get_company_info_category.py
pytdx/parser/get_company_info_content.py
pytdx/parser/get_finance_info.py
pytdx/parser/get_history_minute_time_data.py
pytdx/parser/get_history_transaction_data.py
pytdx/parser/get_index_bars.py
pytdx/parser/get_minute_time_data.py
pytdx/parser/get_security_bars.py
pytdx/parser/get_security_count.py
pytdx/parser/get_security_list.py
pytdx/parser/get_security_quotes.py
pytdx/parser/get_transaction_data.py
pytdx/parser/get_xdxr_info.py
pytdx/parser/raw_parser.py
pytdx/parser/setup_commands.py
pytdx/pool/__init__.py
pytdx/pool/hqpool.py
pytdx/pool/ippool.py
pytdx/reader/__init__.py
pytdx/reader/base_reader.py
pytdx/reader/block_reader.py
pytdx/reader/daily_bar_reader.py
pytdx/reader/exhq_daily_bar_reader.py
pytdx/reader/gbbq_reader.py
pytdx/reader/lc_min_bar_reader.py
pytdx/reader/min_bar_reader.py
pytdx/trade/__init__.py
pytdx/trade/trade.py
pytdx/util/__init__.py
pytdx/util/best_ip.py
pytdx_async.egg-info/PKG-INFO
pytdx_async.egg-info/SOURCES.txt
pytdx_async.egg-info/dependency_links.txt
pytdx_async.egg-info/entry_points.txt
pytdx_async.egg-info/requires.txt
pytdx_async.egg-info/top_level.txt